Metadata-Version: 1.1
Name: smiview
Version: 1.2.1
Summary: smiview is a command-line, text-mode tool to show the structure of a SMILES string.
Home-page: https://bitbucket.org/dalke/smiview
Author: Andrew Dalke
Author-email: dalke@dalkescientific.com
License: MIT
Platform: UNKNOWN
Classifier: Development Status :: 4 - Beta
Classifier: Environment :: Console
Classifier: License :: OSI Approved :: MIT License
Classifier: Operating System :: Unix
Classifier: Programming Language :: Python
Classifier: Programming Language :: Python :: 2.7
Classifier: Programming Language :: Python :: 3
Classifier: Topic :: Scientific/Engineering :: Chemistry
